{"cameraMode":{"drawMode":0,"name":"Shaded","section":"Shading Mode"},"sceneLighting":false,"audioPlay":false,"sceneViewState":{"m_AlwaysRefresh":false,"showFog":true,"showSkybox":false,"showFlares":true,"showImageEffects":true,"showParticleSystems":true,"showVisualEffectGraphs":true,"m_FxEnabled":true},"in2DMode":false,"pivot":{"x":0.0,"y":2.0855937004089357,"z":5.0},"rotation":{"x":-0.26564493775367739,"y":-0.38445883989334109,"z":0.11653400957584381,"w":-0.8763948082923889},"size":0.8144848942756653,"orthographic":true}